mamba_former/__init__.py
mamba_former/main.py
mamba_former-0.0.3.dist-info/LICENSE
mamba_former-0.0.3.dist-info/WHEEL
mamba_former-0.0.3.dist-info/METADATA
mamba_former-0.0.3.dist-info/RECORD
