Metadata-Version: 2.1
Name: mamba-former
Version: 0.0.3
Summary: Paper - Pytorch
Home-page: https://github.com/kyegomez/MambaFormer
License: MIT
Keywords: artificial intelligence,deep learning,optimizers,Prompt Engineering
Author: Kye Gomez
Author-email: kye@apac.ai
Requires-Python: >=3.9,<4.0
Classifier: Development Status :: 4 - Beta
Classifier: Intended Audience :: Developers
Classifier: License :: OSI Approved :: MIT License
Classifier: Programming Language :: Python :: 3
Classifier: Programming Language :: Python :: 3.9
Classifier: Programming Language :: Python :: 3.10
Classifier: Programming Language :: Python :: 3.11
Classifier: Programming Language :: Python :: 3.9
Classifier: Topic :: Scientific/Engineering :: Artificial Intelligence
Requires-Dist: einops
Requires-Dist: torch
Requires-Dist: zetascale (==2.2.7)
Project-URL: Documentation, https://github.com/kyegomez/MambaFormer
Project-URL: Repository, https://github.com/kyegomez/MambaFormer
